[
  {
    "id": "articles-1",
    "type": "card",
    "hidden": true,
    "title": "Sample Article",
    "subTitle": "Subject",
    "description": "",
    "actions": [
      {
        "text": "see more",
        "url": "/details?filepath=/articles/sample-article.json"
      }
    ],
    "images": [
      {
        "text": "sample-article",
        "url": "/projects/images/doge.jpg"
      }
    ],
    "thumbnails": []
  },
  {
    "id": "articles-2",
    "type": "card",
    "hidden": true,
    "title": "Programming Paradigms",
    "subTitle": "Functional Programming, Part 1",
    "description": "",
    "actions": [
      {
        "text": "see more",
        "url": "/details?filepath=/articles/programming-paradigms.json"
      }
    ],
    "images": [
      {
        "text": "programming-paradigms",
        "url": "/articles/images/doge.jpg"
      }
    ],
    "thumbnails": []
  },
  {
    "id": "articles-3",
    "type": "card",
    "title": "Functional Programming",
    "subTitle": "Functional and Reactive Programming, Part 1",
    "description": "",
    "actions": [
      {
        "text": "see more",
        "url": "/details?filepath=/articles/functional-programming.json"
      }
    ],
    "images": [
      {
        "text": "functional-programming",
        "url": "/articles/images/doge.jpg"
      }
    ],
    "thumbnails": []
  }
]
